{
  "Routes": [
    {
      "DownstreamPathTemplate": "/api/auth/login",
      "UpstreamPathTemplate": "/user-service/api/auth/login",
      "UpstreamHttpMethod": ["POST"],
      "DownstreamScheme": "http",
      "DownstreamHostAndPorts": [
        { "Host": "host.docker.internal", "Port": 5034 }
      ]
      // ❌ No AuthenticationOptions → public route
    },

    {
      "DownstreamPathTemplate": "/{everything}",
      "UpstreamPathTemplate": "/user-service/{everything}",
      "UpstreamHttpMethod": ["GET","POST","PUT","DELETE","PATCH"],
      "AuthenticationOptions": {
        "AuthenticationProviderKey": "Bearer"
      },
      "DownstreamScheme": "http",
      "DownstreamHostAndPorts": [
        { "Host": "host.docker.internal", "Port": 5034 }
      ],
      "LoadBalancerOptions": { "Type": "RoundRobin" }
    },

    {
      "UpstreamPathTemplate": "/file-service/{everything}",
      "UpstreamHttpMethod": ["GET","POST","PUT","DELETE"],
      "DownstreamPathTemplate": "/{everything}",
      "DownstreamScheme": "http",
      "DownstreamHostAndPorts": [
        { "Host": "host.docker.internal", "Port": 5035 }
      ],
      "LoadBalancerOptions": { "Type": "RoundRobin" }
    }
  ]
}
